<?xml version="1.0" encoding="utf-8" ?>
<Fax>
  <FaxID>250</FaxID>
  <Owner>DELHI</Owner>
  <IsReceived>True</IsReceived>
  <FileName>In20170929130736420D350D4.tif</FileName>
  <CreateTime>2017-09-29 13:07:42</CreateTime>
  <Pages>1</Pages>
  <Status>DoneOK</Status>  
  <ToFaxNumber></ToFaxNumber>
  <ToCompanyName></ToCompanyName>
  <ToFaxNumber></ToFaxNumber>
  <ToName></ToName>
  <FromName>Test Fax 2</FromName>
  <FromCompanyName></FromCompanyName>
  <FromFaxNumber>0-1000</FromFaxNumber>  
  <SendJobID>0</SendJobID>
  <Matter>29SEP17 13:08</Matter>
  <BillingCode>sachinksalve90@gmail.com</BillingCode>
  <CustomCode1>8</CustomCode1>
  <CustomCode2>Sep 29 2017  1:07PM</CustomCode2>
  <Subject>test</Subject>  
  <FromFaxNumber>0-1000</FromFaxNumber>
  <CallerID>0-1000</CallerID>
</Fax>

